chttp/__init__.py
chttp/__main__.py
chttp/fetch.py
chttp/version.py
tests/test_fetch.py
tests/test_version.py
chttp-0.0.3.dist-info/LICENSE
chttp-0.0.3.dist-info/METADATA
chttp-0.0.3.dist-info/WHEEL
chttp-0.0.3.dist-info/entry_points.txt
chttp-0.0.3.dist-info/top_level.txt
chttp-0.0.3.dist-info/RECORD
