Metadata-Version: 2.1
Name: chttp
Version: 0.0.3
Summary: Concurrent http operations library for Python
Home-page: https://github.com/joaompinto/chttp
Author: João Pinto
Author-email: lamego.pinto@gmail.com
License: MIT
License-File: LICENSE
Requires-Dist: requests
